<?xml version="1.0" encoding="UTF-8"?>
<Document>

	<coordinates>-103.3504432,20.6780057,0.0</coordinates>

	<coordinates>-103.3497995,20.6780158,0.0</coordinates>

	<coordinates>-103.3490056,20.6780408,0.0</coordinates>

	<coordinates>-103.3482009,20.6780509,0.0</coordinates>

	<coordinates>-103.3475035,20.678076,0.0</coordinates>

	<coordinates>-103.3466506,20.6781086,0.0</coordinates>

	<coordinates>-103.3458593,20.6781086,0.0</coordinates>

	<coordinates>-103.3504808,20.6772403,0.0</coordinates>

	<coordinates>-103.3503574,20.6772629,0.0</coordinates>

	<coordinates>-103.348968,20.6773106,0.0</coordinates>

	<coordinates>-103.3497593,20.677273,0.0</coordinates>

	<coordinates>-103.3488178,20.6773533,0.0</coordinates>

	<coordinates>-103.3481553,20.6773533,0.0</coordinates>

	<coordinates>-103.3474821,20.6774035,0.0</coordinates>

	<coordinates>-103.3472809,20.677416,0.0</coordinates>

	<coordinates>-103.3465675,20.6773482,0.0</coordinates>

	<coordinates>-103.3466211,20.6774637,0.0</coordinates>

	<coordinates>-103.3458191,20.6773608,0.0</coordinates>

</Document>
