<?xml version="1.0" encoding="UTF-8"?>

<!-- generated on 9/18/2016 11:10:19 PM by SUMO gui Version 0.25.0
<?xml version="1.0" encoding="UTF-8"?>

<configuration xmlns:xsi="http://www.w3.org/2001/XMLSchema-instance" xsi:noNamespaceSchemaLocation="http://sumo.dlr.de/xsd/sumo-gui.exeConfiguration.xsd">

    <input>
        <net-file value="romaSimulations\data\romaBasic.net.xml"/>
        <route-files value="romaSimulations\data\romaBasic.rou.xml"/>
    </input>

    <output>
        <tripinfo-output value="romaSimulations\data\trip.xml"/>
        <save-state.prefix value="romaSimulations\data\state"/>
    </output>

    <time>
        <begin value="0"/>
        <end value="3600"/>
    </time>

    <report>
        <verbose value="true"/>
        <log value="romaSimulations\data\log.gui"/>
    </report>

    <emissions>
        <phemlight-path value="romaSimulations\data\./PHEMlight/"/>
        <device.emissions.probability value="1"/>
    </emissions>

    <traci_server>
        <remote-port value="8820"/>
    </traci_server>

    <gui_only>
        <gui-settings-file value="romaSimulations\data\romaBasic.settings.xml"/>
        <start value="true"/>
    </gui_only>

</configuration>
-->

<tripinfos xmlns:xsi="http://www.w3.org/2001/XMLSchema-instance" xsi:noNamespaceSchemaLocation="http://sumo.dlr.de/xsd/tripinfo_file.xsd">
    <tripinfo id="veh1" depart="3.00" departLane="E5_0" departPos="6.10" departSpeed="0.00" departDelay="3.00" arrival="82.00" arrivalLane="E2_1" arrivalPos="242.71" arrivalSpeed="13.32" duration="79.00" routeLength="474.52" waitSteps="35" timeLoss="44.44" rerouteNo="0" devices="tripinfo_veh1 emissions_veh1" vType="CarA" vaporized="">
        <emissions CO_abs="1051.266141" CO2_abs="97711.934442" HC_abs="30.003093" PMx_abs="9.650330" NOx_abs="193.033073" fuel_abs="38.956252"/>
    </tripinfo>
    <tripinfo id="veh0" depart="0.00" departLane="E5_0" departPos="6.10" departSpeed="0.00" departDelay="0.00" arrival="82.00" arrivalLane="E2_0" arrivalPos="242.71" arrivalSpeed="13.00" duration="82.00" routeLength="474.52" waitSteps="36" timeLoss="46.88" rerouteNo="0" devices="tripinfo_veh0 emissions_veh0" vType="CarA" vaporized="">
        <emissions CO_abs="1113.793898" CO2_abs="103100.933513" HC_abs="31.357897" PMx_abs="10.496456" NOx_abs="204.908673" fuel_abs="41.104765"/>
    </tripinfo>
    <tripinfo id="veh3" depart="9.00" departLane="E5_0" departPos="6.10" departSpeed="0.00" departDelay="9.00" arrival="84.00" arrivalLane="E2_1" arrivalPos="242.71" arrivalSpeed="12.64" duration="75.00" routeLength="474.52" waitSteps="30" timeLoss="40.55" rerouteNo="0" devices="tripinfo_veh3 emissions_veh3" vType="CarA" vaporized="">
        <emissions CO_abs="1057.098926" CO2_abs="99413.466049" HC_abs="29.782854" PMx_abs="10.083489" NOx_abs="197.309040" fuel_abs="39.634628"/>
    </tripinfo>
    <tripinfo id="veh2" depart="6.00" departLane="E5_0" departPos="6.10" departSpeed="0.00" departDelay="6.00" arrival="84.00" arrivalLane="E2_0" arrivalPos="242.71" arrivalSpeed="13.77" duration="78.00" routeLength="474.52" waitSteps="34" timeLoss="43.24" rerouteNo="0" devices="tripinfo_veh2 emissions_veh2" vType="CarA" vaporized="">
        <emissions CO_abs="1059.494886" CO2_abs="104497.840430" HC_abs="31.543105" PMx_abs="9.871367" NOx_abs="203.740764" fuel_abs="41.661691"/>
    </tripinfo>
    <tripinfo id="veh5" depart="15.00" departLane="E5_0" departPos="6.10" departSpeed="0.00" departDelay="15.00" arrival="86.00" arrivalLane="E2_1" arrivalPos="242.71" arrivalSpeed="13.06" duration="71.00" routeLength="474.52" waitSteps="26" timeLoss="36.39" rerouteNo="0" devices="tripinfo_veh5 emissions_veh5" vType="CarA" vaporized="">
        <emissions CO_abs="1049.727017" CO2_abs="96500.558880" HC_abs="28.961558" PMx_abs="9.804806" NOx_abs="192.632010" fuel_abs="38.473296"/>
    </tripinfo>
    <tripinfo id="veh4" depart="12.00" departLane="E5_0" departPos="6.10" departSpeed="0.00" departDelay="12.00" arrival="86.00" arrivalLane="E2_0" arrivalPos="242.71" arrivalSpeed="13.85" duration="74.00" routeLength="474.52" waitSteps="28" timeLoss="39.14" rerouteNo="0" devices="tripinfo_veh4 emissions_veh4" vType="CarA" vaporized="">
        <emissions CO_abs="1260.109507" CO2_abs="105756.881921" HC_abs="32.522395" PMx_abs="11.291805" NOx_abs="215.608502" fuel_abs="42.163648"/>
    </tripinfo>
    <tripinfo id="veh7" depart="21.00" departLane="E5_0" departPos="6.10" departSpeed="0.00" departDelay="21.00" arrival="88.00" arrivalLane="E2_1" arrivalPos="242.71" arrivalSpeed="13.12" duration="67.00" routeLength="474.52" waitSteps="20" timeLoss="32.24" rerouteNo="0" devices="tripinfo_veh7 emissions_veh7" vType="CarA" vaporized="">
        <emissions CO_abs="1110.363412" CO2_abs="99757.343359" HC_abs="29.843510" PMx_abs="10.123777" NOx_abs="200.491656" fuel_abs="39.771725"/>
    </tripinfo>
    <tripinfo id="veh6" depart="18.00" departLane="E5_0" departPos="6.10" departSpeed="0.00" departDelay="18.00" arrival="88.00" arrivalLane="E2_0" arrivalPos="242.71" arrivalSpeed="13.24" duration="70.00" routeLength="474.52" waitSteps="23" timeLoss="34.90" rerouteNo="0" devices="tripinfo_veh6 emissions_veh6" vType="CarA" vaporized="">
        <emissions CO_abs="1056.795318" CO2_abs="96076.373092" HC_abs="28.296444" PMx_abs="9.878440" NOx_abs="193.526879" fuel_abs="38.304179"/>
    </tripinfo>
    <tripinfo id="veh8" depart="24.00" departLane="E5_0" departPos="6.10" departSpeed="0.00" departDelay="24.00" arrival="89.00" arrivalLane="E2_0" arrivalPos="242.71" arrivalSpeed="12.61" duration="65.00" routeLength="474.52" waitSteps="20" timeLoss="30.79" rerouteNo="0" devices="tripinfo_veh8 emissions_veh8" vType="CarA" vaporized="">
        <emissions CO_abs="1031.250476" CO2_abs="100309.134616" HC_abs="28.776206" PMx_abs="10.110951" NOx_abs="199.799182" fuel_abs="39.991719"/>
    </tripinfo>
    <tripinfo id="veh9" depart="27.00" departLane="E5_0" departPos="6.10" departSpeed="0.00" departDelay="27.00" arrival="90.00" arrivalLane="E2_1" arrivalPos="242.71" arrivalSpeed="13.29" duration="63.00" routeLength="474.52" waitSteps="16" timeLoss="28.14" rerouteNo="0" devices="tripinfo_veh9 emissions_veh9" vType="CarA" vaporized="">
        <emissions CO_abs="1137.297874" CO2_abs="97973.353481" HC_abs="29.541902" PMx_abs="10.392428" NOx_abs="199.315257" fuel_abs="39.060475"/>
    </tripinfo>
    <tripinfo id="veh10" depart="30.00" departLane="E5_0" departPos="6.10" departSpeed="0.00" departDelay="30.00" arrival="91.00" arrivalLane="E2_0" arrivalPos="242.71" arrivalSpeed="13.62" duration="61.00" routeLength="474.52" waitSteps="15" timeLoss="26.48" rerouteNo="0" devices="tripinfo_veh10 emissions_veh10" vType="CarA" vaporized="">
        <emissions CO_abs="1142.282011" CO2_abs="99359.290800" HC_abs="29.763027" PMx_abs="10.419478" NOx_abs="201.780854" fuel_abs="39.613027"/>
    </tripinfo>
    <tripinfo id="veh11" depart="33.00" departLane="E5_0" departPos="6.10" departSpeed="0.00" departDelay="33.00" arrival="92.00" arrivalLane="E2_1" arrivalPos="242.71" arrivalSpeed="13.82" duration="59.00" routeLength="474.52" waitSteps="14" timeLoss="24.26" rerouteNo="0" devices="tripinfo_veh11 emissions_veh11" vType="CarA" vaporized="">
        <emissions CO_abs="1075.483220" CO2_abs="101534.881226" HC_abs="29.613482" PMx_abs="10.164337" NOx_abs="202.721135" fuel_abs="40.480405"/>
    </tripinfo>
    <tripinfo id="veh12" depart="36.00" departLane="E5_0" departPos="6.10" departSpeed="0.00" departDelay="36.00" arrival="93.00" arrivalLane="E2_0" arrivalPos="242.71" arrivalSpeed="13.03" duration="57.00" routeLength="474.52" waitSteps="12" timeLoss="22.32" rerouteNo="0" devices="tripinfo_veh12 emissions_veh12" vType="CarA" vaporized="">
        <emissions CO_abs="1000.302416" CO2_abs="98891.916476" HC_abs="28.302808" PMx_abs="9.731559" NOx_abs="196.039994" fuel_abs="39.426698"/>
    </tripinfo>
    <tripinfo id="veh13" depart="39.00" departLane="E5_0" departPos="6.10" departSpeed="0.00" departDelay="39.00" arrival="94.00" arrivalLane="E2_1" arrivalPos="242.71" arrivalSpeed="13.75" duration="55.00" routeLength="474.52" waitSteps="6" timeLoss="20.18" rerouteNo="0" devices="tripinfo_veh13 emissions_veh13" vType="CarA" vaporized="">
        <emissions CO_abs="1012.439254" CO2_abs="91268.304848" HC_abs="27.093699" PMx_abs="9.381532" NOx_abs="183.846925" fuel_abs="36.387275"/>
    </tripinfo>
    <tripinfo id="veh15" depart="45.00" departLane="E5_0" departPos="6.10" departSpeed="0.00" departDelay="45.00" arrival="140.00" arrivalLane="E2_1" arrivalPos="242.71" arrivalSpeed="13.05" duration="95.00" routeLength="474.52" waitSteps="42" timeLoss="60.24" rerouteNo="0" devices="tripinfo_veh15 emissions_veh15" vType="CarA" vaporized="">
        <emissions CO_abs="1439.278658" CO2_abs="118042.967510" HC_abs="38.512433" PMx_abs="12.577445" NOx_abs="238.254085" fuel_abs="47.061915"/>
    </tripinfo>
    <tripinfo id="veh14" depart="42.00" departLane="E5_0" departPos="6.10" departSpeed="0.00" departDelay="42.00" arrival="140.00" arrivalLane="E2_0" arrivalPos="242.71" arrivalSpeed="12.67" duration="98.00" routeLength="474.52" waitSteps="45" timeLoss="63.02" rerouteNo="0" devices="tripinfo_veh14 emissions_veh14" vType="CarA" vaporized="">
        <emissions CO_abs="1385.300686" CO2_abs="117150.176857" HC_abs="37.733008" PMx_abs="12.194682" NOx_abs="234.854631" fuel_abs="46.705973"/>
    </tripinfo>
    <tripinfo id="veh17" depart="51.00" departLane="E5_0" departPos="6.10" departSpeed="0.00" departDelay="51.00" arrival="142.00" arrivalLane="E2_1" arrivalPos="242.71" arrivalSpeed="13.65" duration="91.00" routeLength="474.52" waitSteps="38" timeLoss="56.20" rerouteNo="0" devices="tripinfo_veh17 emissions_veh17" vType="CarA" vaporized="">
        <emissions CO_abs="1302.990436" CO2_abs="116431.713820" HC_abs="36.582707" PMx_abs="11.708485" NOx_abs="231.135481" fuel_abs="46.419536"/>
    </tripinfo>
    <tripinfo id="veh16" depart="48.00" departLane="E5_0" departPos="6.10" departSpeed="0.00" departDelay="48.00" arrival="142.00" arrivalLane="E2_0" arrivalPos="242.71" arrivalSpeed="13.57" duration="94.00" routeLength="474.52" waitSteps="39" timeLoss="58.97" rerouteNo="0" devices="tripinfo_veh16 emissions_veh16" vType="CarA" vaporized="">
        <emissions CO_abs="1289.544008" CO2_abs="114241.631728" HC_abs="36.395803" PMx_abs="11.538033" NOx_abs="226.493575" fuel_abs="45.546383"/>
    </tripinfo>
    <tripinfo id="veh19" depart="57.00" departLane="E5_0" departPos="6.10" departSpeed="0.00" departDelay="57.00" arrival="144.00" arrivalLane="E2_1" arrivalPos="242.71" arrivalSpeed="13.34" duration="87.00" routeLength="474.52" waitSteps="37" timeLoss="52.44" rerouteNo="0" devices="tripinfo_veh19 emissions_veh19" vType="CarA" vaporized="">
        <emissions CO_abs="1272.353261" CO2_abs="108671.117867" HC_abs="33.974942" PMx_abs="11.535953" NOx_abs="219.561544" fuel_abs="43.325505"/>
    </tripinfo>
    <tripinfo id="veh18" depart="54.00" departLane="E5_0" departPos="6.10" departSpeed="0.00" departDelay="54.00" arrival="144.00" arrivalLane="E2_0" arrivalPos="242.71" arrivalSpeed="13.71" duration="90.00" routeLength="474.52" waitSteps="36" timeLoss="54.92" rerouteNo="0" devices="tripinfo_veh18 emissions_veh18" vType="CarA" vaporized="">
        <emissions CO_abs="1446.164167" CO2_abs="125755.834583" HC_abs="39.287766" PMx_abs="13.057615" NOx_abs="252.457720" fuel_abs="50.136921"/>
    </tripinfo>
    <tripinfo id="veh20" depart="60.00" departLane="E5_0" departPos="6.10" departSpeed="0.00" departDelay="60.00" arrival="145.00" arrivalLane="E2_0" arrivalPos="242.71" arrivalSpeed="13.62" duration="85.00" routeLength="474.52" waitSteps="36" timeLoss="50.76" rerouteNo="0" devices="tripinfo_veh20 emissions_veh20" vType="CarA" vaporized="">
        <emissions CO_abs="1293.307851" CO2_abs="115408.534152" HC_abs="35.909958" PMx_abs="11.661809" NOx_abs="229.858362" fuel_abs="46.011612"/>
    </tripinfo>
    <tripinfo id="veh21" depart="63.00" departLane="E5_0" departPos="6.10" departSpeed="0.00" departDelay="63.00" arrival="146.00" arrivalLane="E2_1" arrivalPos="242.71" arrivalSpeed="13.88" duration="83.00" routeLength="474.52" waitSteps="38" timeLoss="48.52" rerouteNo="0" devices="tripinfo_veh21 emissions_veh21" vType="CarA" vaporized="">
        <emissions CO_abs="1217.068409" CO2_abs="108449.950429" HC_abs="33.368719" PMx_abs="11.099557" NOx_abs="216.988829" fuel_abs="43.237334"/>
    </tripinfo>
    <tripinfo id="veh22" depart="66.00" departLane="E5_0" departPos="6.10" departSpeed="0.00" departDelay="66.00" arrival="147.00" arrivalLane="E2_0" arrivalPos="242.71" arrivalSpeed="13.47" duration="81.00" routeLength="474.52" waitSteps="36" timeLoss="46.73" rerouteNo="0" devices="tripinfo_veh22 emissions_veh22" vType="CarA" vaporized="">
        <emissions CO_abs="1093.672589" CO2_abs="99612.456688" HC_abs="30.571022" PMx_abs="9.940594" NOx_abs="197.955784" fuel_abs="39.713961"/>
    </tripinfo>
    <tripinfo id="veh23" depart="69.00" departLane="E5_0" departPos="6.10" departSpeed="0.00" departDelay="69.00" arrival="148.00" arrivalLane="E2_1" arrivalPos="242.71" arrivalSpeed="13.53" duration="79.00" routeLength="474.52" waitSteps="32" timeLoss="44.63" rerouteNo="0" devices="tripinfo_veh23 emissions_veh23" vType="CarA" vaporized="">
        <emissions CO_abs="1057.399588" CO2_abs="102185.340717" HC_abs="30.499871" PMx_abs="9.933534" NOx_abs="201.269914" fuel_abs="40.739731"/>
    </tripinfo>
    <tripinfo id="veh24" depart="72.00" departLane="E5_0" departPos="6.10" departSpeed="0.00" departDelay="72.00" arrival="149.00" arrivalLane="E2_0" arrivalPos="242.71" arrivalSpeed="13.13" duration="77.00" routeLength="474.52" waitSteps="32" timeLoss="42.59" rerouteNo="0" devices="tripinfo_veh24 emissions_veh24" vType="CarA" vaporized="">
        <emissions CO_abs="1112.540453" CO2_abs="99628.450028" HC_abs="30.448028" PMx_abs="10.336351" NOx_abs="199.617937" fuel_abs="39.720338"/>
    </tripinfo>
    <tripinfo id="veh25" depart="75.00" departLane="E5_0" departPos="6.10" departSpeed="0.00" departDelay="75.00" arrival="150.00" arrivalLane="E2_1" arrivalPos="242.71" arrivalSpeed="13.06" duration="75.00" routeLength="474.52" waitSteps="29" timeLoss="40.68" rerouteNo="0" devices="tripinfo_veh25 emissions_veh25" vType="CarA" vaporized="">
        <emissions CO_abs="999.459625" CO2_abs="100487.024255" HC_abs="29.385397" PMx_abs="9.801140" NOx_abs="197.190230" fuel_abs="40.062641"/>
    </tripinfo>
    <tripinfo id="veh26" depart="78.00" departLane="E5_0" departPos="6.10" departSpeed="0.00" departDelay="78.00" arrival="151.00" arrivalLane="E2_0" arrivalPos="242.71" arrivalSpeed="13.41" duration="73.00" routeLength="474.52" waitSteps="27" timeLoss="38.58" rerouteNo="0" devices="tripinfo_veh26 emissions_veh26" vType="CarA" vaporized="">
        <emissions CO_abs="1124.127890" CO2_abs="100371.546598" HC_abs="30.654793" PMx_abs="10.445548" NOx_abs="201.316001" fuel_abs="40.016599"/>
    </tripinfo>
    <tripinfo id="veh27" depart="81.00" departLane="E5_0" departPos="6.10" departSpeed="0.00" departDelay="81.00" arrival="153.00" arrivalLane="E2_1" arrivalPos="242.71" arrivalSpeed="13.32" duration="72.00" routeLength="474.52" waitSteps="24" timeLoss="36.88" rerouteNo="0" devices="tripinfo_veh27 emissions_veh27" vType="CarA" vaporized="">
        <emissions CO_abs="1017.627671" CO2_abs="101212.964750" HC_abs="29.511671" PMx_abs="9.966107" NOx_abs="199.379966" fuel_abs="40.352061"/>
    </tripinfo>
    <tripinfo id="veh29" depart="87.00" departLane="E5_0" departPos="6.10" departSpeed="0.00" departDelay="87.00" arrival="198.00" arrivalLane="E2_1" arrivalPos="242.71" arrivalSpeed="13.69" duration="111.00" routeLength="474.52" waitSteps="59" timeLoss="76.11" rerouteNo="0" devices="tripinfo_veh29 emissions_veh29" vType="CarA" vaporized="">
        <emissions CO_abs="1427.335616" CO2_abs="129391.790662" HC_abs="40.790823" PMx_abs="12.866134" NOx_abs="255.470252" fuel_abs="51.586521"/>
    </tripinfo>
    <tripinfo id="veh28" depart="84.00" departLane="E5_0" departPos="6.10" departSpeed="0.00" departDelay="84.00" arrival="198.00" arrivalLane="E2_0" arrivalPos="242.71" arrivalSpeed="13.71" duration="114.00" routeLength="474.52" waitSteps="62" timeLoss="79.15" rerouteNo="0" devices="tripinfo_veh28 emissions_veh28" vType="CarA" vaporized="">
        <emissions CO_abs="1510.138862" CO2_abs="124944.187393" HC_abs="40.268594" PMx_abs="13.316087" NOx_abs="252.501824" fuel_abs="49.813327"/>
    </tripinfo>
    <tripinfo id="veh31" depart="93.00" departLane="E5_0" departPos="6.10" departSpeed="0.00" departDelay="93.00" arrival="200.00" arrivalLane="E2_1" arrivalPos="242.71" arrivalSpeed="12.92" duration="107.00" routeLength="474.52" waitSteps="52" timeLoss="72.41" rerouteNo="0" devices="tripinfo_veh31 emissions_veh31" vType="CarA" vaporized="">
        <emissions CO_abs="1330.587853" CO2_abs="116972.495518" HC_abs="37.267390" PMx_abs="11.787559" NOx_abs="232.345581" fuel_abs="46.635136"/>
    </tripinfo>
    <tripinfo id="veh30" depart="90.00" departLane="E5_0" departPos="6.10" departSpeed="0.00" departDelay="90.00" arrival="201.00" arrivalLane="E2_0" arrivalPos="242.71" arrivalSpeed="13.41" duration="111.00" routeLength="474.52" waitSteps="56" timeLoss="75.84" rerouteNo="0" devices="tripinfo_veh30 emissions_veh30" vType="CarA" vaporized="">
        <emissions CO_abs="1339.240437" CO2_abs="123301.659929" HC_abs="38.576993" PMx_abs="12.302881" NOx_abs="243.139202" fuel_abs="49.158481"/>
    </tripinfo>
    <tripinfo id="veh33" depart="100.00" departLane="E5_0" departPos="6.10" departSpeed="0.00" departDelay="40.00" arrival="202.00" arrivalLane="E2_1" arrivalPos="242.71" arrivalSpeed="12.93" duration="102.00" routeLength="474.52" waitSteps="48" timeLoss="67.35" rerouteNo="0" devices="tripinfo_veh33 emissions_veh33" vType="CarA" vaporized="">
        <emissions CO_abs="1416.888999" CO2_abs="115445.846683" HC_abs="37.727261" PMx_abs="12.512670" NOx_abs="233.721397" fuel_abs="46.026482"/>
    </tripinfo>
    <tripinfo id="veh32" depart="97.00" departLane="E5_0" departPos="6.10" departSpeed="0.00" departDelay="37.00" arrival="202.00" arrivalLane="E2_0" arrivalPos="242.71" arrivalSpeed="13.41" duration="105.00" routeLength="474.52" waitSteps="52" timeLoss="70.75" rerouteNo="0" devices="tripinfo_veh32 emissions_veh32" vType="CarA" vaporized="">
        <emissions CO_abs="1359.602396" CO2_abs="124405.748047" HC_abs="39.284041" PMx_abs="12.284064" NOx_abs="244.879958" fuel_abs="49.598661"/>
    </tripinfo>
    <tripinfo id="veh35" depart="106.00" departLane="E5_0" departPos="6.10" departSpeed="0.00" departDelay="46.00" arrival="204.00" arrivalLane="E2_1" arrivalPos="242.71" arrivalSpeed="12.76" duration="98.00" routeLength="474.52" waitSteps="41" timeLoss="63.36" rerouteNo="0" devices="tripinfo_veh35 emissions_veh35" vType="CarA" vaporized="">
        <emissions CO_abs="1260.455499" CO2_abs="111476.402047" HC_abs="35.164030" PMx_abs="11.563056" NOx_abs="222.119547" fuel_abs="44.443929"/>
    </tripinfo>
    <tripinfo id="veh34" depart="103.00" departLane="E5_0" departPos="6.10" departSpeed="0.00" departDelay="43.00" arrival="204.00" arrivalLane="E2_0" arrivalPos="242.71" arrivalSpeed="13.35" duration="101.00" routeLength="474.52" waitSteps="49" timeLoss="66.71" rerouteNo="0" devices="tripinfo_veh34 emissions_veh34" vType="CarA" vaporized="">
        <emissions CO_abs="1311.879233" CO2_abs="118892.827246" HC_abs="37.733342" PMx_abs="11.784972" NOx_abs="234.242063" fuel_abs="47.400744"/>
    </tripinfo>
    <tripinfo id="veh36" depart="109.00" departLane="E5_0" departPos="6.10" departSpeed="0.00" departDelay="49.00" arrival="206.00" arrivalLane="E2_0" arrivalPos="242.71" arrivalSpeed="13.81" duration="97.00" routeLength="474.52" waitSteps="42" timeLoss="62.58" rerouteNo="0" devices="tripinfo_veh36 emissions_veh36" vType="CarA" vaporized="">
        <emissions CO_abs="1329.851201" CO2_abs="115259.254253" HC_abs="36.696326" PMx_abs="11.772201" NOx_abs="230.068078" fuel_abs="45.952092"/>
    </tripinfo>
    <tripinfo id="veh37" depart="112.00" departLane="E5_0" departPos="6.10" departSpeed="0.00" departDelay="52.00" arrival="207.00" arrivalLane="E2_1" arrivalPos="242.71" arrivalSpeed="13.23" duration="95.00" routeLength="474.52" waitSteps="39" timeLoss="59.89" rerouteNo="0" devices="tripinfo_veh37 emissions_veh37" vType="CarA" vaporized="">
        <emissions CO_abs="1335.376881" CO2_abs="117421.661118" HC_abs="37.448838" PMx_abs="11.669982" NOx_abs="232.840274" fuel_abs="46.814211"/>
    </tripinfo>
    <tripinfo id="veh38" depart="115.00" departLane="E5_0" departPos="6.10" departSpeed="0.00" departDelay="55.00" arrival="208.00" arrivalLane="E2_0" arrivalPos="242.71" arrivalSpeed="13.68" duration="93.00" routeLength="474.52" waitSteps="36" timeLoss="58.48" rerouteNo="0" devices="tripinfo_veh38 emissions_veh38" vType="CarA" vaporized="">
        <emissions CO_abs="1345.252754" CO2_abs="117465.071446" HC_abs="36.789549" PMx_abs="12.139269" NOx_abs="235.238831" fuel_abs="46.831519"/>
    </tripinfo>
    <tripinfo id="veh39" depart="118.00" departLane="E5_0" departPos="6.10" departSpeed="0.00" departDelay="58.00" arrival="209.00" arrivalLane="E2_1" arrivalPos="242.71" arrivalSpeed="12.62" duration="91.00" routeLength="474.52" waitSteps="35" timeLoss="56.00" rerouteNo="0" devices="tripinfo_veh39 emissions_veh39" vType="CarA" vaporized="">
        <emissions CO_abs="1265.917474" CO2_abs="118157.018761" HC_abs="36.414976" PMx_abs="11.633337" NOx_abs="232.872290" fuel_abs="47.107390"/>
    </tripinfo>
    <tripinfo id="veh40" depart="122.00" departLane="E5_0" departPos="6.10" departSpeed="0.00" departDelay="62.00" arrival="210.00" arrivalLane="E2_0" arrivalPos="242.71" arrivalSpeed="13.76" duration="88.00" routeLength="474.52" waitSteps="35" timeLoss="53.64" rerouteNo="0" devices="tripinfo_veh40 emissions_veh40" vType="CarA" vaporized="">
        <emissions CO_abs="1197.698691" CO2_abs="103707.073703" HC_abs="33.061114" PMx_abs="10.550792" NOx_abs="206.896605" fuel_abs="41.346416"/>
    </tripinfo>
    <tripinfo id="veh41" depart="125.00" departLane="E5_0" departPos="6.10" departSpeed="0.00" departDelay="65.00" arrival="212.00" arrivalLane="E2_1" arrivalPos="242.71" arrivalSpeed="13.79" duration="87.00" routeLength="474.52" waitSteps="36" timeLoss="52.00" rerouteNo="0" devices="tripinfo_veh41 emissions_veh41" vType="CarA" vaporized="">
        <emissions CO_abs="1223.137671" CO2_abs="111578.409714" HC_abs="34.057170" PMx_abs="11.227884" NOx_abs="222.170136" fuel_abs="44.484600"/>
    </tripinfo>
    <tripinfo id="veh43" depart="131.00" departLane="E5_0" departPos="6.10" departSpeed="0.00" departDelay="71.00" arrival="255.00" arrivalLane="E2_1" arrivalPos="242.71" arrivalSpeed="13.45" duration="124.00" routeLength="474.52" waitSteps="71" timeLoss="89.67" rerouteNo="0" devices="tripinfo_veh43 emissions_veh43" vType="CarA" vaporized="">
        <emissions CO_abs="1365.227883" CO2_abs="121797.557074" HC_abs="39.192450" PMx_abs="12.273700" NOx_abs="240.288763" fuel_abs="48.558816"/>
    </tripinfo>
    <tripinfo id="veh42" depart="128.00" departLane="E5_0" departPos="6.10" departSpeed="0.00" departDelay="68.00" arrival="256.00" arrivalLane="E2_0" arrivalPos="242.71" arrivalSpeed="13.03" duration="128.00" routeLength="474.52" waitSteps="74" timeLoss="93.17" rerouteNo="0" devices="tripinfo_veh42 emissions_veh42" vType="CarA" vaporized="">
        <emissions CO_abs="1457.141983" CO2_abs="126991.135693" HC_abs="41.558475" PMx_abs="12.897042" NOx_abs="251.068934" fuel_abs="50.629414"/>
    </tripinfo>
    <tripinfo id="veh45" depart="138.00" departLane="E5_0" departPos="6.10" departSpeed="0.00" departDelay="78.00" arrival="258.00" arrivalLane="E2_1" arrivalPos="242.71" arrivalSpeed="13.02" duration="120.00" routeLength="474.52" waitSteps="65" timeLoss="85.09" rerouteNo="0" devices="tripinfo_veh45 emissions_veh45" vType="CarA" vaporized="">
        <emissions CO_abs="1376.774279" CO2_abs="123849.643055" HC_abs="39.796583" PMx_abs="12.375013" NOx_abs="243.723739" fuel_abs="49.376949"/>
    </tripinfo>
    <tripinfo id="veh44" depart="135.00" departLane="E5_0" departPos="6.10" departSpeed="0.00" departDelay="75.00" arrival="258.00" arrivalLane="E2_0" arrivalPos="242.71" arrivalSpeed="12.66" duration="123.00" routeLength="474.52" waitSteps="69" timeLoss="88.17" rerouteNo="0" devices="tripinfo_veh44 emissions_veh44" vType="CarA" vaporized="">
        <emissions CO_abs="1505.873784" CO2_abs="127772.117616" HC_abs="41.494403" PMx_abs="13.313766" NOx_abs="255.507035" fuel_abs="50.940779"/>
    </tripinfo>
    <tripinfo id="veh47" depart="144.00" departLane="E5_0" departPos="6.10" departSpeed="0.00" departDelay="84.00" arrival="260.00" arrivalLane="E2_1" arrivalPos="242.71" arrivalSpeed="13.70" duration="116.00" routeLength="474.52" waitSteps="60" timeLoss="81.19" rerouteNo="0" devices="tripinfo_veh47 emissions_veh47" vType="CarA" vaporized="">
        <emissions CO_abs="1335.613776" CO2_abs="124207.788456" HC_abs="39.081977" PMx_abs="12.231282" NOx_abs="243.672089" fuel_abs="49.519738"/>
    </tripinfo>
    <tripinfo id="veh46" depart="141.00" departLane="E5_0" departPos="6.10" departSpeed="0.00" departDelay="81.00" arrival="260.00" arrivalLane="E2_0" arrivalPos="242.71" arrivalSpeed="13.75" duration="119.00" routeLength="474.52" waitSteps="64" timeLoss="84.07" rerouteNo="0" devices="tripinfo_veh46 emissions_veh46" vType="CarA" vaporized="">
        <emissions CO_abs="1599.023500" CO2_abs="132773.566064" HC_abs="43.143068" PMx_abs="14.083327" NOx_abs="267.309679" fuel_abs="52.934780"/>
    </tripinfo>
    <tripinfo id="veh49" depart="150.00" departLane="E5_0" departPos="6.10" departSpeed="0.00" departDelay="90.00" arrival="262.00" arrivalLane="E2_1" arrivalPos="242.71" arrivalSpeed="13.22" duration="112.00" routeLength="474.52" waitSteps="54" timeLoss="77.29" rerouteNo="0" devices="tripinfo_veh49 emissions_veh49" vType="CarA" vaporized="">
        <emissions CO_abs="1251.635891" CO2_abs="116377.847182" HC_abs="36.494357" PMx_abs="11.465743" NOx_abs="228.545655" fuel_abs="46.398059"/>
    </tripinfo>
    <tripinfo id="veh48" depart="147.00" departLane="E5_0" departPos="6.10" departSpeed="0.00" departDelay="87.00" arrival="262.00" arrivalLane="E2_0" arrivalPos="242.71" arrivalSpeed="12.87" duration="115.00" routeLength="474.52" waitSteps="61" timeLoss="80.34" rerouteNo="0" devices="tripinfo_veh48 emissions_veh48" vType="CarA" vaporized="">
        <emissions CO_abs="1377.595515" CO2_abs="116518.915103" HC_abs="37.504360" PMx_abs="12.217580" NOx_abs="233.733326" fuel_abs="46.454300"/>
    </tripinfo>
    <tripinfo id="veh51" depart="156.00" departLane="E5_0" departPos="6.10" departSpeed="0.00" departDelay="96.00" arrival="264.00" arrivalLane="E2_1" arrivalPos="242.71" arrivalSpeed="13.04" duration="108.00" routeLength="474.52" waitSteps="50" timeLoss="73.19" rerouteNo="0" devices="tripinfo_veh51 emissions_veh51" vType="CarA" vaporized="">
        <emissions CO_abs="1471.729299" CO2_abs="127341.508321" HC_abs="40.543245" PMx_abs="12.941954" NOx_abs="254.183080" fuel_abs="50.769102"/>
    </tripinfo>
    <tripinfo id="veh50" depart="153.00" departLane="E5_0" departPos="6.10" departSpeed="0.00" departDelay="93.00" arrival="264.00" arrivalLane="E2_0" arrivalPos="242.71" arrivalSpeed="13.37" duration="111.00" routeLength="474.52" waitSteps="56" timeLoss="76.33" rerouteNo="0" devices="tripinfo_veh50 emissions_veh50" vType="CarA" vaporized="">
        <emissions CO_abs="1352.272148" CO2_abs="120820.412511" HC_abs="38.653932" PMx_abs="12.113210" NOx_abs="238.657103" fuel_abs="48.169242"/>
    </tripinfo>
    <tripinfo id="veh53" depart="162.00" departLane="E5_0" departPos="6.10" departSpeed="0.00" departDelay="102.00" arrival="266.00" arrivalLane="E2_1" arrivalPos="242.71" arrivalSpeed="13.31" duration="104.00" routeLength="474.52" waitSteps="47" timeLoss="69.01" rerouteNo="0" devices="tripinfo_veh53 emissions_veh53" vType="CarA" vaporized="">
        <emissions CO_abs="1287.657463" CO2_abs="117564.832412" HC_abs="37.109160" PMx_abs="11.639822" NOx_abs="231.609623" fuel_abs="46.871292"/>
    </tripinfo>
    <tripinfo id="veh52" depart="159.00" departLane="E5_0" departPos="6.10" departSpeed="0.00" departDelay="99.00" arrival="266.00" arrivalLane="E2_0" arrivalPos="242.71" arrivalSpeed="13.61" duration="107.00" routeLength="474.52" waitSteps="50" timeLoss="72.42" rerouteNo="0" devices="tripinfo_veh52 emissions_veh52" vType="CarA" vaporized="">
        <emissions CO_abs="1252.357663" CO2_abs="122166.426823" HC_abs="37.317475" PMx_abs="11.754031" NOx_abs="238.406857" fuel_abs="48.705883"/>
    </tripinfo>
    <tripinfo id="veh55" depart="168.00" departLane="E5_0" departPos="6.10" departSpeed="0.00" departDelay="108.00" arrival="268.00" arrivalLane="E2_1" arrivalPos="242.71" arrivalSpeed="13.52" duration="100.00" routeLength="474.52" waitSteps="42" timeLoss="64.81" rerouteNo="0" devices="tripinfo_veh55 emissions_veh55" vType="CarA" vaporized="">
        <emissions CO_abs="1348.216263" CO2_abs="119489.827295" HC_abs="37.573849" PMx_abs="12.213683" NOx_abs="237.841966" fuel_abs="47.638758"/>
    </tripinfo>
    <tripinfo id="veh54" depart="165.00" departLane="E5_0" departPos="6.10" departSpeed="0.00" departDelay="105.00" arrival="268.00" arrivalLane="E2_0" arrivalPos="242.71" arrivalSpeed="12.92" duration="103.00" routeLength="474.52" waitSteps="45" timeLoss="68.36" rerouteNo="0" devices="tripinfo_veh54 emissions_veh54" vType="CarA" vaporized="">
        <emissions CO_abs="1333.038018" CO2_abs="124091.714535" HC_abs="38.501111" PMx_abs="12.446797" NOx_abs="244.698945" fuel_abs="49.473464"/>
    </tripinfo>
    <tripinfo id="veh56" depart="171.00" departLane="E5_0" departPos="6.10" departSpeed="0.00" departDelay="111.00" arrival="314.00" arrivalLane="E2_0" arrivalPos="242.71" arrivalSpeed="12.95" duration="143.00" routeLength="474.52" waitSteps="77" timeLoss="108.23" rerouteNo="0" devices="tripinfo_veh56 emissions_veh56" vType="CarA" vaporized="">
        <emissions CO_abs="1559.470806" CO2_abs="136507.532567" HC_abs="45.454988" PMx_abs="13.489917" NOx_abs="267.634649" fuel_abs="54.423450"/>
    </tripinfo>
    <tripinfo id="veh57" depart="174.00" departLane="E5_0" departPos="6.10" departSpeed="0.00" departDelay="114.00" arrival="315.00" arrivalLane="E2_1" arrivalPos="242.71" arrivalSpeed="13.72" duration="141.00" routeLength="474.52" waitSteps="76" timeLoss="106.03" rerouteNo="0" devices="tripinfo_veh57 emissions_veh57" vType="CarA" vaporized="">
        <emissions CO_abs="1608.581139" CO2_abs="141533.902412" HC_abs="46.940329" PMx_abs="13.890451" NOx_abs="277.145567" fuel_abs="56.427387"/>
    </tripinfo>
    <tripinfo id="veh58" depart="178.00" departLane="E5_0" departPos="6.10" departSpeed="0.00" departDelay="118.00" arrival="316.00" arrivalLane="E2_0" arrivalPos="242.71" arrivalSpeed="13.17" duration="138.00" routeLength="474.52" waitSteps="73" timeLoss="103.12" rerouteNo="0" devices="tripinfo_veh58 emissions_veh58" vType="CarA" vaporized="">
        <emissions CO_abs="1700.277580" CO2_abs="136680.786556" HC_abs="46.039853" PMx_abs="14.576665" NOx_abs="274.906182" fuel_abs="54.492521"/>
    </tripinfo>
    <tripinfo id="veh59" depart="181.00" departLane="E5_0" departPos="6.10" departSpeed="0.00" departDelay="121.00" arrival="317.00" arrivalLane="E2_1" arrivalPos="242.71" arrivalSpeed="13.01" duration="136.00" routeLength="474.52" waitSteps="71" timeLoss="101.14" rerouteNo="0" devices="tripinfo_veh59 emissions_veh59" vType="CarA" vaporized="">
        <emissions CO_abs="1546.014988" CO2_abs="128725.929607" HC_abs="42.131912" PMx_abs="13.331643" NOx_abs="257.872250" fuel_abs="51.321044"/>
    </tripinfo>
    <tripinfo id="veh60" depart="184.00" departLane="E5_0" departPos="6.10" departSpeed="0.00" departDelay="124.00" arrival="318.00" arrivalLane="E2_0" arrivalPos="242.71" arrivalSpeed="12.96" duration="134.00" routeLength="474.52" waitSteps="70" timeLoss="99.04" rerouteNo="0" devices="tripinfo_veh60 emissions_veh60" vType="CarA" vaporized="">
        <emissions CO_abs="1703.988755" CO2_abs="136695.953696" HC_abs="44.805980" PMx_abs="15.168229" NOx_abs="278.078035" fuel_abs="54.498570"/>
    </tripinfo>
    <tripinfo id="veh61" depart="187.00" departLane="E5_0" departPos="6.10" departSpeed="0.00" departDelay="127.00" arrival="319.00" arrivalLane="E2_1" arrivalPos="242.71" arrivalSpeed="13.40" duration="132.00" routeLength="474.52" waitSteps="70" timeLoss="97.00" rerouteNo="0" devices="tripinfo_veh61 emissions_veh61" vType="CarA" vaporized="">
        <emissions CO_abs="1376.935429" CO2_abs="114930.938838" HC_abs="38.784800" PMx_abs="11.735927" NOx_abs="227.879041" fuel_abs="45.821193"/>
    </tripinfo>
    <tripinfo id="veh62" depart="191.00" departLane="E5_0" departPos="6.10" departSpeed="0.00" departDelay="131.00" arrival="320.00" arrivalLane="E2_0" arrivalPos="242.71" arrivalSpeed="13.85" duration="129.00" routeLength="474.52" waitSteps="68" timeLoss="93.98" rerouteNo="0" devices="tripinfo_veh62 emissions_veh62" vType="CarA" vaporized="">
        <emissions CO_abs="1389.159996" CO2_abs="123404.127959" HC_abs="39.625712" PMx_abs="12.338636" NOx_abs="243.826375" fuel_abs="49.199329"/>
    </tripinfo>
    <tripinfo id="veh63" depart="194.00" departLane="E5_0" departPos="6.10" departSpeed="0.00" departDelay="74.00" arrival="321.00" arrivalLane="E2_1" arrivalPos="242.71" arrivalSpeed="12.92" duration="127.00" routeLength="474.52" waitSteps="70" timeLoss="91.95" rerouteNo="0" devices="tripinfo_veh63 emissions_veh63" vType="CarA" vaporized="">
        <emissions CO_abs="1399.790486" CO2_abs="120780.273129" HC_abs="39.292182" PMx_abs="12.355693" NOx_abs="239.954198" fuel_abs="48.153236"/>
    </tripinfo>
    <tripinfo id="veh64" depart="197.00" departLane="E5_0" departPos="6.10" departSpeed="0.00" departDelay="77.00" arrival="322.00" arrivalLane="E2_0" arrivalPos="242.71" arrivalSpeed="13.25" duration="125.00" routeLength="474.52" waitSteps="66" timeLoss="90.16" rerouteNo="0" devices="tripinfo_veh64 emissions_veh64" vType="CarA" vaporized="">
        <emissions CO_abs="1369.944475" CO2_abs="117486.886594" HC_abs="37.404419" PMx_abs="12.150885" NOx_abs="235.408328" fuel_abs="46.840215"/>
    </tripinfo>
    <tripinfo id="veh65" depart="200.00" departLane="E5_0" departPos="6.10" departSpeed="0.00" departDelay="80.00" arrival="323.00" arrivalLane="E2_1" arrivalPos="242.71" arrivalSpeed="12.84" duration="123.00" routeLength="474.52" waitSteps="70" timeLoss="87.87" rerouteNo="0" devices="tripinfo_veh65 emissions_veh65" vType="CarA" vaporized="">
        <emissions CO_abs="1399.037299" CO2_abs="121004.262391" HC_abs="38.837397" PMx_abs="12.439173" NOx_abs="241.193143" fuel_abs="48.242540"/>
    </tripinfo>
    <tripinfo id="veh67" depart="206.00" departLane="E5_0" departPos="6.10" departSpeed="0.00" departDelay="86.00" arrival="324.00" arrivalLane="E2_1" arrivalPos="242.71" arrivalSpeed="13.09" duration="118.00" routeLength="474.52" waitSteps="63" timeLoss="83.75" rerouteNo="0" devices="tripinfo_veh67 emissions_veh67" vType="CarA" vaporized="">
        <emissions CO_abs="1303.729218" CO2_abs="117636.237983" HC_abs="37.542975" PMx_abs="11.658176" NOx_abs="231.714482" fuel_abs="46.899760"/>
    </tripinfo>
    <tripinfo id="veh66" depart="203.00" departLane="E5_0" departPos="6.10" departSpeed="0.00" departDelay="83.00" arrival="324.00" arrivalLane="E2_0" arrivalPos="242.71" arrivalSpeed="13.08" duration="121.00" routeLength="474.52" waitSteps="63" timeLoss="85.99" rerouteNo="0" devices="tripinfo_veh66 emissions_veh66" vType="CarA" vaporized="">
        <emissions CO_abs="1394.058421" CO2_abs="121022.365590" HC_abs="38.451148" PMx_abs="12.334426" NOx_abs="241.486773" fuel_abs="48.249757"/>
    </tripinfo>
    <tripinfo id="veh69" depart="212.00" departLane="E5_0" departPos="6.10" departSpeed="0.00" departDelay="92.00" arrival="326.00" arrivalLane="E2_1" arrivalPos="242.71" arrivalSpeed="13.71" duration="114.00" routeLength="474.52" waitSteps="57" timeLoss="79.50" rerouteNo="0" devices="tripinfo_veh69 emissions_veh69" vType="CarA" vaporized="">
        <emissions CO_abs="1341.421112" CO2_abs="117333.256597" HC_abs="37.101348" PMx_abs="12.061431" NOx_abs="234.140273" fuel_abs="46.778967"/>
    </tripinfo>
    <tripinfo id="veh68" depart="209.00" departLane="E5_0" departPos="6.10" departSpeed="0.00" departDelay="89.00" arrival="326.00" arrivalLane="E2_0" arrivalPos="242.71" arrivalSpeed="13.30" duration="117.00" routeLength="474.52" waitSteps="59" timeLoss="81.87" rerouteNo="0" devices="tripinfo_veh68 emissions_veh68" vType="CarA" vaporized="">
        <emissions CO_abs="1402.714720" CO2_abs="122862.507148" HC_abs="38.989069" PMx_abs="12.724764" NOx_abs="245.083234" fuel_abs="48.983394"/>
    </tripinfo>
    <tripinfo id="veh71" depart="218.00" departLane="E5_0" departPos="6.10" departSpeed="0.00" departDelay="98.00" arrival="372.00" arrivalLane="E2_1" arrivalPos="242.71" arrivalSpeed="13.77" duration="154.00" routeLength="474.52" waitSteps="89" timeLoss="119.45" rerouteNo="0" devices="tripinfo_veh71 emissions_veh71" vType="CarA" vaporized="">
        <emissions CO_abs="1788.884481" CO2_abs="148817.654822" HC_abs="49.529128" PMx_abs="15.503522" NOx_abs="296.951093" fuel_abs="59.331305"/>
    </tripinfo>
    <tripinfo id="veh70" depart="215.00" departLane="E5_0" departPos="6.10" departSpeed="0.00" departDelay="95.00" arrival="372.00" arrivalLane="E2_0" arrivalPos="242.71" arrivalSpeed="12.96" duration="157.00" routeLength="474.52" waitSteps="90" timeLoss="122.09" rerouteNo="0" devices="tripinfo_veh70 emissions_veh70" vType="CarA" vaporized="">
        <emissions CO_abs="1858.237538" CO2_abs="145272.669481" HC_abs="48.884221" PMx_abs="15.934811" NOx_abs="295.299081" fuel_abs="57.917973"/>
    </tripinfo>
    <tripinfo id="veh73" depart="225.00" departLane="E5_0" departPos="6.10" departSpeed="0.00" departDelay="105.00" arrival="374.00" arrivalLane="E2_1" arrivalPos="242.71" arrivalSpeed="13.09" duration="149.00" routeLength="474.52" waitSteps="83" timeLoss="114.34" rerouteNo="0" devices="tripinfo_veh73 emissions_veh73" vType="CarA" vaporized="">
        <emissions CO_abs="1722.035765" CO2_abs="143332.339942" HC_abs="48.183787" PMx_abs="14.832762" NOx_abs="285.010019" fuel_abs="57.144393"/>
    </tripinfo>
    <tripinfo id="veh72" depart="221.00" departLane="E5_0" departPos="6.10" departSpeed="0.00" departDelay="101.00" arrival="374.00" arrivalLane="E2_0" arrivalPos="242.71" arrivalSpeed="13.00" duration="153.00" routeLength="474.52" waitSteps="86" timeLoss="118.12" rerouteNo="0" devices="tripinfo_veh72 emissions_veh72" vType="CarA" vaporized="">
        <emissions CO_abs="1584.518393" CO2_abs="126103.880335" HC_abs="42.548042" PMx_abs="13.568941" NOx_abs="254.468183" fuel_abs="50.275670"/>
    </tripinfo>
    <tripinfo id="veh75" depart="231.00" departLane="E5_0" departPos="6.10" departSpeed="0.00" departDelay="111.00" arrival="376.00" arrivalLane="E2_1" arrivalPos="242.71" arrivalSpeed="12.74" duration="145.00" routeLength="474.52" waitSteps="78" timeLoss="110.41" rerouteNo="0" devices="tripinfo_veh75 emissions_veh75" vType="CarA" vaporized="">
        <emissions CO_abs="1623.511666" CO2_abs="137390.683807" HC_abs="45.616669" PMx_abs="13.993175" NOx_abs="272.680159" fuel_abs="54.775547"/>
    </tripinfo>
    <tripinfo id="veh74" depart="228.00" departLane="E5_0" departPos="6.10" departSpeed="0.00" departDelay="108.00" arrival="376.00" arrivalLane="E2_0" arrivalPos="242.71" arrivalSpeed="13.29" duration="148.00" routeLength="474.52" waitSteps="80" timeLoss="112.98" rerouteNo="0" devices="tripinfo_veh74 emissions_veh74" vType="CarA" vaporized="">
        <emissions CO_abs="1469.788223" CO2_abs="135817.250583" HC_abs="43.738301" PMx_abs="13.125038" NOx_abs="264.714858" fuel_abs="54.148248"/>
    </tripinfo>
    <tripinfo id="veh77" depart="237.00" departLane="E5_0" departPos="6.10" departSpeed="0.00" departDelay="117.00" arrival="378.00" arrivalLane="E2_1" arrivalPos="242.71" arrivalSpeed="13.28" duration="141.00" routeLength="474.52" waitSteps="72" timeLoss="106.47" rerouteNo="0" devices="tripinfo_veh77 emissions_veh77" vType="CarA" vaporized="">
        <emissions CO_abs="1573.798405" CO2_abs="132594.731137" HC_abs="43.761528" PMx_abs="13.819362" NOx_abs="264.463346" fuel_abs="52.863475"/>
    </tripinfo>
    <tripinfo id="veh76" depart="234.00" departLane="E5_0" departPos="6.10" departSpeed="0.00" departDelay="114.00" arrival="378.00" arrivalLane="E2_0" arrivalPos="242.71" arrivalSpeed="13.47" duration="144.00" routeLength="474.52" waitSteps="75" timeLoss="108.90" rerouteNo="0" devices="tripinfo_veh76 emissions_veh76" vType="CarA" vaporized="">
        <emissions CO_abs="1626.464320" CO2_abs="138910.161307" HC_abs="45.164185" PMx_abs="14.394587" NOx_abs="276.961922" fuel_abs="55.381343"/>
    </tripinfo>
    <tripinfo id="veh78" depart="240.00" departLane="E5_0" departPos="6.10" departSpeed="0.00" departDelay="120.00" arrival="379.00" arrivalLane="E2_0" arrivalPos="242.71" arrivalSpeed="13.76" duration="139.00" routeLength="474.52" waitSteps="68" timeLoss="104.61" rerouteNo="0" devices="tripinfo_veh78 emissions_veh78" vType="CarA" vaporized="">
        <emissions CO_abs="1507.396083" CO2_abs="130547.230983" HC_abs="42.791883" PMx_abs="13.131853" NOx_abs="258.216695" fuel_abs="52.047170"/>
    </tripinfo>
    <tripinfo id="veh79" depart="243.00" departLane="E5_0" departPos="6.10" departSpeed="0.00" departDelay="123.00" arrival="380.00" arrivalLane="E2_1" arrivalPos="242.71" arrivalSpeed="12.87" duration="137.00" routeLength="474.52" waitSteps="69" timeLoss="102.55" rerouteNo="0" devices="tripinfo_veh79 emissions_veh79" vType="CarA" vaporized="">
        <emissions CO_abs="1384.161355" CO2_abs="124992.730117" HC_abs="40.750487" PMx_abs="12.065829" NOx_abs="244.163915" fuel_abs="49.832675"/>
    </tripinfo>
    <tripinfo id="veh80" depart="246.00" departLane="E5_0" departPos="6.10" departSpeed="0.00" departDelay="126.00" arrival="381.00" arrivalLane="E2_0" arrivalPos="242.71" arrivalSpeed="12.66" duration="135.00" routeLength="474.52" waitSteps="65" timeLoss="100.67" rerouteNo="0" devices="tripinfo_veh80 emissions_veh80" vType="CarA" vaporized="">
        <emissions CO_abs="1459.021708" CO2_abs="122722.120774" HC_abs="40.630847" PMx_abs="12.629370" NOx_abs="244.361758" fuel_abs="48.927416"/>
    </tripinfo>
    <tripinfo id="veh81" depart="249.00" departLane="E5_0" departPos="6.10" departSpeed="0.00" departDelay="129.00" arrival="382.00" arrivalLane="E2_1" arrivalPos="242.71" arrivalSpeed="12.79" duration="133.00" routeLength="474.52" waitSteps="68" timeLoss="98.50" rerouteNo="0" devices="tripinfo_veh81 emissions_veh81" vType="CarA" vaporized="">
        <emissions CO_abs="1043.939520" CO2_abs="108229.679658" HC_abs="33.304925" PMx_abs="10.088781" NOx_abs="207.359776" fuel_abs="43.149510"/>
    </tripinfo>
    <tripinfo id="veh82" depart="253.00" departLane="E5_0" departPos="6.10" departSpeed="0.00" departDelay="133.00" arrival="384.00" arrivalLane="E2_1" arrivalPos="242.71" arrivalSpeed="13.05" duration="131.00" routeLength="474.52" waitSteps="68" timeLoss="96.29" rerouteNo="0" devices="tripinfo_veh82 emissions_veh82" vType="CarA" vaporized="">
        <emissions CO_abs="1284.762969" CO2_abs="115515.526858" HC_abs="36.905733" PMx_abs="11.833022" NOx_abs="228.309502" fuel_abs="46.054265"/>
    </tripinfo>
    <tripinfo id="veh83" depart="256.00" departLane="E5_0" departPos="6.10" departSpeed="0.00" departDelay="136.00" arrival="384.00" arrivalLane="E2_0" arrivalPos="242.71" arrivalSpeed="13.14" duration="128.00" routeLength="474.52" waitSteps="65" timeLoss="92.87" rerouteNo="0" devices="tripinfo_veh83 emissions_veh83" vType="CarA" vaporized="">
        <emissions CO_abs="1338.338008" CO2_abs="123961.586258" HC_abs="39.671197" PMx_abs="12.045937" NOx_abs="241.864519" fuel_abs="49.421581"/>
    </tripinfo>
    <tripinfo id="veh84" depart="259.00" departLane="E5_0" departPos="6.10" departSpeed="0.00" departDelay="139.00" arrival="430.00" arrivalLane="E2_1" arrivalPos="242.71" arrivalSpeed="13.01" duration="171.00" routeLength="474.52" waitSteps="104" timeLoss="136.32" rerouteNo="0" devices="tripinfo_veh84 emissions_veh84" vType="CarA" vaporized="">
        <emissions CO_abs="1791.960727" CO2_abs="143107.363927" HC_abs="49.403254" PMx_abs="15.219636" NOx_abs="286.188481" fuel_abs="57.054698"/>
    </tripinfo>
    <tripinfo id="veh85" depart="262.00" departLane="E5_0" departPos="6.10" departSpeed="0.00" departDelay="142.00" arrival="430.00" arrivalLane="E2_0" arrivalPos="242.71" arrivalSpeed="13.09" duration="168.00" routeLength="474.52" waitSteps="104" timeLoss="133.40" rerouteNo="0" devices="tripinfo_veh85 emissions_veh85" vType="CarA" vaporized="">
        <emissions CO_abs="1702.851216" CO2_abs="138834.198003" HC_abs="47.058719" PMx_abs="14.595209" NOx_abs="277.316501" fuel_abs="55.351054"/>
    </tripinfo>
    <tripinfo id="veh87" depart="268.00" departLane="E5_0" departPos="6.10" departSpeed="0.00" departDelay="148.00" arrival="432.00" arrivalLane="E2_1" arrivalPos="242.71" arrivalSpeed="13.20" duration="164.00" routeLength="474.52" waitSteps="97" timeLoss="129.31" rerouteNo="0" devices="tripinfo_veh87 emissions_veh87" vType="CarA" vaporized="">
        <emissions CO_abs="1640.099654" CO2_abs="135645.156267" HC_abs="45.427428" PMx_abs="14.068347" NOx_abs="270.595365" fuel_abs="54.079632"/>
    </tripinfo>
    <tripinfo id="veh86" depart="265.00" departLane="E5_0" departPos="6.10" departSpeed="0.00" departDelay="145.00" arrival="432.00" arrivalLane="E2_0" arrivalPos="242.71" arrivalSpeed="12.69" duration="167.00" routeLength="474.52" waitSteps="101" timeLoss="132.35" rerouteNo="0" devices="tripinfo_veh86 emissions_veh86" vType="CarA" vaporized="">
        <emissions CO_abs="1677.864895" CO2_abs="137534.624238" HC_abs="46.932383" PMx_abs="14.216929" NOx_abs="273.440856" fuel_abs="54.832932"/>
    </tripinfo>
    <tripinfo id="veh89" depart="274.00" departLane="E5_0" departPos="6.10" departSpeed="0.00" departDelay="154.00" arrival="434.00" arrivalLane="E2_1" arrivalPos="242.71" arrivalSpeed="12.74" duration="160.00" routeLength="474.52" waitSteps="92" timeLoss="125.38" rerouteNo="0" devices="tripinfo_veh89 emissions_veh89" vType="CarA" vaporized="">
        <emissions CO_abs="1618.960900" CO2_abs="141004.601493" HC_abs="46.193908" PMx_abs="14.202133" NOx_abs="278.561504" fuel_abs="56.216363"/>
    </tripinfo>
    <tripinfo id="veh88" depart="271.00" departLane="E5_0" departPos="6.10" departSpeed="0.00" departDelay="151.00" arrival="434.00" arrivalLane="E2_0" arrivalPos="242.71" arrivalSpeed="13.58" duration="163.00" routeLength="474.52" waitSteps="99" timeLoss="128.11" rerouteNo="0" devices="tripinfo_veh88 emissions_veh88" vType="CarA" vaporized="">
        <emissions CO_abs="1728.404051" CO2_abs="146379.335317" HC_abs="49.408053" PMx_abs="14.702643" NOx_abs="288.615222" fuel_abs="58.359185"/>
    </tripinfo>
    <tripinfo id="veh91" depart="280.00" departLane="E5_0" departPos="6.10" departSpeed="0.00" departDelay="160.00" arrival="436.00" arrivalLane="E2_1" arrivalPos="242.71" arrivalSpeed="13.75" duration="156.00" routeLength="474.52" waitSteps="87" timeLoss="121.37" rerouteNo="0" devices="tripinfo_veh91 emissions_veh91" vType="CarA" vaporized="">
        <emissions CO_abs="1632.614682" CO2_abs="136975.703702" HC_abs="45.091660" PMx_abs="14.296484" NOx_abs="273.574939" fuel_abs="54.610103"/>
    </tripinfo>
    <tripinfo id="veh90" depart="277.00" departLane="E5_0" departPos="6.10" departSpeed="0.00" departDelay="157.00" arrival="436.00" arrivalLane="E2_0" arrivalPos="242.71" arrivalSpeed="12.62" duration="159.00" routeLength="474.52" waitSteps="92" timeLoss="124.33" rerouteNo="0" devices="tripinfo_veh90 emissions_veh90" vType="CarA" vaporized="">
        <emissions CO_abs="1492.451912" CO2_abs="131604.602231" HC_abs="44.107236" PMx_abs="12.934226" NOx_abs="256.953066" fuel_abs="52.468726"/>
    </tripinfo>
    <tripinfo id="veh93" depart="286.00" departLane="E5_0" departPos="6.10" departSpeed="0.00" departDelay="106.00" arrival="438.00" arrivalLane="E2_1" arrivalPos="242.71" arrivalSpeed="13.20" duration="152.00" routeLength="474.52" waitSteps="80" timeLoss="117.29" rerouteNo="0" devices="tripinfo_veh93 emissions_veh93" vType="CarA" vaporized="">
        <emissions CO_abs="1488.749553" CO2_abs="124978.684440" HC_abs="42.000133" PMx_abs="12.797693" NOx_abs="247.785790" fuel_abs="49.827074"/>
    </tripinfo>
    <tripinfo id="veh92" depart="283.00" departLane="E5_0" departPos="6.10" departSpeed="0.00" departDelay="163.00" arrival="438.00" arrivalLane="E2_0" arrivalPos="242.71" arrivalSpeed="12.61" duration="155.00" routeLength="474.52" waitSteps="88" timeLoss="120.35" rerouteNo="0" devices="tripinfo_veh92 emissions_veh92" vType="CarA" vaporized="">
        <emissions CO_abs="1529.617427" CO2_abs="131435.731155" HC_abs="43.582635" PMx_abs="13.495478" NOx_abs="259.994980" fuel_abs="52.401401"/>
    </tripinfo>
    <tripinfo id="veh95" depart="292.00" departLane="E5_0" departPos="6.10" departSpeed="0.00" departDelay="112.00" arrival="440.00" arrivalLane="E2_1" arrivalPos="242.71" arrivalSpeed="12.87" duration="148.00" routeLength="474.52" waitSteps="75" timeLoss="113.13" rerouteNo="0" devices="tripinfo_veh95 emissions_veh95" vType="CarA" vaporized="">
        <emissions CO_abs="1473.553957" CO2_abs="121293.219859" HC_abs="40.897305" PMx_abs="12.613499" NOx_abs="241.843583" fuel_abs="48.357734"/>
    </tripinfo>
    <tripinfo id="veh94" depart="289.00" departLane="E5_0" departPos="6.10" departSpeed="0.00" departDelay="109.00" arrival="440.00" arrivalLane="E2_0" arrivalPos="242.71" arrivalSpeed="13.02" duration="151.00" routeLength="474.52" waitSteps="81" timeLoss="116.24" rerouteNo="0" devices="tripinfo_veh94 emissions_veh94" vType="CarA" vaporized="">
        <emissions CO_abs="1400.090137" CO2_abs="124068.620012" HC_abs="41.175646" PMx_abs="12.196515" NOx_abs="242.621939" fuel_abs="49.464246"/>
    </tripinfo>
    <tripinfo id="veh97" depart="298.00" departLane="E5_0" departPos="6.10" departSpeed="0.00" departDelay="118.00" arrival="442.00" arrivalLane="E2_1" arrivalPos="242.71" arrivalSpeed="13.22" duration="144.00" routeLength="474.52" waitSteps="73" timeLoss="109.02" rerouteNo="0" devices="tripinfo_veh97 emissions_veh97" vType="CarA" vaporized="">
        <emissions CO_abs="1456.329370" CO2_abs="127042.726335" HC_abs="41.903502" PMx_abs="12.772800" NOx_abs="250.225907" fuel_abs="50.649977"/>
    </tripinfo>
    <tripinfo id="veh96" depart="295.00" departLane="E5_0" departPos="6.10" departSpeed="0.00" departDelay="115.00" arrival="442.00" arrivalLane="E2_0" arrivalPos="242.71" arrivalSpeed="13.67" duration="147.00" routeLength="474.52" waitSteps="75" timeLoss="112.02" rerouteNo="0" devices="tripinfo_veh96 emissions_veh96" vType="CarA" vaporized="">
        <emissions CO_abs="1326.271531" CO2_abs="125805.126688" HC_abs="40.086213" PMx_abs="12.025880" NOx_abs="244.233684" fuel_abs="50.156569"/>
    </tripinfo>
</tripinfos>
